zuper_proc_local.pyi
zuper_proc_local.cpython-310-aarch64-linux-gnu.so
zuper_proc_local_z7-7.3.2201261049.dist-info/METADATA
zuper_proc_local_z7-7.3.2201261049.dist-info/WHEEL
zuper_proc_local_z7-7.3.2201261049.dist-info/top_level.txt
zuper_proc_local_z7-7.3.2201261049.dist-info/zip-safe
zuper_proc_local_z7-7.3.2201261049.dist-info/RECORD
