Metadata-Version: 2.1
Name: zuper-proc-local-z7
Version: 7.3.2201261049
Summary: UNKNOWN
Home-page: https://github.com/zupermind/zuper-proc-local
Author: Andrea Censi
Author-email: info@zupermind.com
License: UNKNOWN
Platform: UNKNOWN
Requires-Dist: zuper-commons-z7
Requires-Dist: zuper-utils-asyncio-z7
Requires-Dist: zuper-zapp-interfaces-z7
Requires-Dist: zuper-zapp-z7
Provides-Extra: test
Requires-Dist: zuper-fs-local-z7 ; extra == 'test'
Requires-Dist: zuper-loghandle-z7 ; extra == 'test'
Requires-Dist: zuper-notes-z7 ; extra == 'test'
Requires-Dist: zuper-proc-local-z7 ; extra == 'test'
Requires-Dist: zuper-zapp-z7 ; extra == 'test'
